--[[
COMMANDS:

;kick plr - Kicks a player using potato method
;ban plr - Bans a player using potato method
;saveban plr Bans a player using potato but it saves to a file lol
;gearbl - This will disable the custom gear blacklist for tools like the vampire gear
;clr - clears the map, credit to webs
;breakperm - ONLY WORKS WELL IN A BRAND NEW SERVER SINCE THE GAME CACHES PERM
;antipotato - Makes it impossible for you to get gears at all, no potato nor buckets for instance.
;iy -- loads infinite yield
;unpunish -- Unpunish without admin. Useless if u have perm
;examplecommand - You have to edit this yourself, it's easy to understand

]]

--loadstring(game:HttpGet(('https://raw.githubusercontent.com/Tech-187/BetterIY/refs/heads/main/BetterIYMain.lua'),true))() -- IY is not really necessary but if you plan on using IY in any way then uncomment this line of code

if not _G.Barloaded then
    _G.Barloaded = true
    loadstring(game:HttpGet(('https://raw.githubusercontent.com/Tech-187/Temp/refs/heads/main/v3-bar-src'),true))()
end

repeat task.wait() until game:IsLoaded()

local screenGui = Instance.new("ScreenGui")
screenGui.Parent = game.Players.LocalPlayer:WaitForChild("PlayerGui")

local Stable_Check = false
local rotation = Instance.new("BodyGyro")
local plrs = game:GetService("Players")
local getplrs = plrs:GetChildren()
local plr = plrs.LocalPlayer
local mouse = plr:GetMouse()
local Character = plr.Character or plr.CharacterAdded
local hum = Character:WaitForChild("Humanoid")
local Plrname = plr.Name
local userId = game.Players.LocalPlayer.UserId
local antivg = true
local nocgear = false
_G.IYMODE = true

-- useless
local pcall = pcall
local task = task

--local plrs = game:GetService'Players'
local kickwl = {""..plr.Name..""}

_G.Banned = { { "p", "SlenderMan990921" } } -- p aka potato is the only method at the moment
local BlacklistedGear = {"VampireVanquisher","IvoryPeriastron","PaintBucket","SubspaceTripmine","Transmorpher","LaserFingerPointers","SeaThemedCrossbow","RageTable","IceStaff","AzureDragonMagicSlayerSword","ViridianThrowingKnives","PrettyPrettyPrincessSceptor","OrinthianSwordAndShield","AR","AlienEgg","BarrelOfMonkeys","AnAlpacaYouKnow","BoneSword","WormholeTunneler","GiantAnimeHammer","FakeChartreusePeriastron","SkeletonScythe","BlizzardWand","SentryTurret","StatueStaffOfStonyJustice","TacticalAirstrike","Tactical Airstrike","Easterbomby","RainbowPeriastron","RemoteExplosiveDetonator","BeachUmbrella","ChickThrowingStars","CloverThrowingStars","GoldShuriken","MetallicThrowingKnives","NeonNinjaThrowingStars","TransparentThrowingStars","InstantTreehouse"} -- findtool gearcloner - fast gearname finder without exploits
local gearwhitelisted = {} -- Players that are in this table won't get ungeared.
local connections = {}

game:GetService("Workspace").FallenPartsDestroyHeight = 0/0

local invisiblebox = Instance.new("TextBox", workspace)

local function chatt(massage)
    invisiblebox:SetTextFromInput(massage)
    game.Players:Chat(massage)
end

local loopnum = "99999999999999999999999999999999"
local antilog = "00000000000000000000000000000000"


local function GetPad(msg)
    while PadCheck == true do
        task.wait(0)
        if not game:GetService("Workspace").Terrain["_Game"].Admin.Pads:FindFirstChild(game.Players.LocalPlayer.Name .. "'s admin") then
            if game:GetService("Workspace").Terrain["_Game"].Admin.Pads:FindFirstChild("Touch to get admin") then
                local pad = game:GetService("Workspace").Terrain["_Game"].Admin.Pads:FindFirstChild("Touch to get admin"):FindFirstChild("Head")
                local padCFrame = game:GetService("Workspace").Terrain["_Game"].Admin.Pads:FindFirstChild("Touch to get admin"):FindFirstChild("Head").CFrame
                task.wait(0.125)
                pad.CanCollide = false
                repeat task.wait() until game.Players.LocalPlayer.Character:FindFirstChild("HumanoidRootPart")
                pad.CFrame = game.Players.LocalPlayer.Character.HumanoidRootPart.CFrame
                task.wait(0.125)
                pad.CFrame = padCFrame
                pad.CanCollide = true
            else
                fireclickdetector(game:GetService("Workspace").Terrain._Game.Admin.Regen.ClickDetector, 0)
            end
        end
    end
end

connections[#connections + 1] = game:GetService("RunService").RenderStepped:Connect(function()
    task.spawn(function()
        if antivg == true then
            for i, player in pairs(game:GetService("Players"):GetPlayers()) do
                if player.Name ~= plr.Name and not table.find(gearwhitelisted, player.Name) then
                if player.Character then
			for i, gear in ipairs(BlacklistedGear) do
  			   if player.Backpack:FindFirstChild(gear) or player.Character:FindFirstChild(gear) then
                        local plrname = player.Name
                        game.Players:Chat("ungear "..plrname) -- spammy as fuck but will do I guess
                        wait(.35)
                     end
		     end
                end
                end
            end
        end
    end)
end) -- My indenting is terrible here because I made many mistakes and I'm too lazy to fix the indenting

--// Gamepass checker \\--

task.spawn(function()
    pcall(function()
        local MarketplaceService = game:GetService("MarketplaceService")
        local pc1 = (MarketplaceService:UserOwnsGamePassAsync(plr.UserId, 66254) or MarketplaceService:UserOwnsGamePassAsync(plr.UserId, 64354) or MarketplaceService:UserOwnsGamePassAsync(plr.UserId, 35748) or MarketplaceService:UserOwnsGamePassAsync(plr.UserId, 37127) or MarketplaceService:UserOwnsGamePassAsync(plr.UserId, 735344035))
        pc1exists = true
        if pc1 then
            print("Perm found")
        else
            PadCheck = true
            GetPad(msg)
            print("Perm not found. Enabling pad grabber")
            local screenGui = Instance.new("ScreenGui")
            screenGui.Parent = game.Players.LocalPlayer:WaitForChild("PlayerGui")

            local textLabel = Instance.new("TextLabel")
            textLabel.Parent = screenGui
            textLabel.Text = "Your account does not have Perm Admin \n Therefore perm admin has been \n more or less granted to you \n for free."
            textLabel.Size = UDim2.new(0, 300, 0, 150)
            textLabel.Position = UDim2.new(0.5, -50, 0.5, -25)
            textLabel.TextXAlignment = Enum.TextXAlignment.Center
            textLabel.TextYAlignment = Enum.TextYAlignment.Center

            textLabel.Visible = true

            wait(4.5)

            textLabel.Visible = false
        end
    end)
    wait(1)
    if not pc1exists then
        print("PERM WAS UNABLE TO BE CHECKED")
    end
end)

_G.prefix = ";"

local admin = {prefix = _G.prefix, version = "v3 all over again lmao"}
local commands = {}
local descriptions = {}
local http = game:GetService("HttpService")
local plyrs = game:GetService("Players")

function addcommand(cmdName, cmdDescription, cmdFunction)
    commands[cmdName] = cmdName
    descriptions[cmdName] = cmdDescription
    plr.Chatted:Connect(function(msg)
            msg = msg:lower()
            args = msg:split(" ")
            if args[1] == admin.prefix .. cmdName then
                cmdFunction()
            elseif args[1] == "/e" and args[2] == admin.prefix .. cmdName then
                args[2] = args[3]
                cmdFunction()
            end
        end)
end

function GetPlayer(target)
    local plrs = game:service("Players"):GetPlayers()
    if target:lower() == "all" then
        return plrs
    elseif target:lower() == "others" then
        for index, plr in pairs(plrs) do
            if plr == game:service("Players").LocalPlayer then
                table.remove(plrs, index)
                return plrs
            end
        end
    elseif target:lower() == "me" then
        return {game:service("Players").LocalPlayer}
    else
        local plrTargets = {}
        for index, plr in pairs(plrs) do
            if plr.Name:sub(1, #target):lower() == target:lower() or plr.DisplayName:sub(1, #target):lower() == target:lower()  then
                table.insert(plrTargets, plr)
            end
        end
        return plrTargets
    end
end

addcommand("ban",
"bans a mf",
function()
    for _Index, Target in pairs(GetPlayer(args[2])) do
        chatt(_G.prefix.."kick "..Target.Name.." fuck")
        table.insert(_G.Banned, { "p", Target.Name })
    end
end)

addcommand("saveban",
"saves the banned mf to a file",
function()
    for _Index, Target in pairs(GetPlayer(args[2])) do
        appendfile("scv3bans.txt", Target.Name.."\n")

        local function stored(plrname)
            for _, entry in ipairs(_G.Banned) do
                if entry[2] == plrname then
                    return true
                end
            end
            return false
        end
        if not stored(Target.Name) then
            chatt(_G.prefix.."kick "..Target.Name.." fuck")
            table.insert(_G.Banned, { "p", Target.Name })
        end
    end
end)

addcommand("examplecommand",
"Good example",
function()
    for _Index, Target in pairs(GetPlayer(args[2])) do
    chatt("command here")
    chatt("command to "..Target.Name.." here")
    chatt("An example would be")
    chatt("kill "..Target.Name)
    end
end)

addcommand("antipotato",
"former name, no client gear",
function()
    nocgear = true
    while nocgear do task.wait()
        if _G.IYMODE then
            execCmd("removetools")
        else
            chatt("iyc removetools") -- only works with better iy
        end
    end
end)

addcommand("unantipotato",
"former name, no client gear",
function()
    nocgear = false
end)

addcommand("iy",
"infinite yield",
function()
    _G.IYMODE = true
    loadstring(game:HttpGet(('https://raw.githubusercontent.com/Tech-187/BetterIY/refs/heads/main/BetterIYMain.lua'),true))()
end)

addcommand("clr",
"credit, webs",
function()
    local tool = plr.Backpack:FindFirstChild("Delete") or plr.Character:FindFirstChild("Delete")

    if not tool then
        chatt("btools me")
    end
    
    chatt("lock all")

    local function jonathan()
        local deleteTool = plr.Backpack:FindFirstChild("Delete") or plr.Character:FindFirstChild("Delete")
        return deleteTool and deleteTool:FindFirstChild("RemoteEvent")
    end

    local remote;
    for _ = 1, 40 do
        remote = jonathan()
        if remote then break end
        task.wait()
    end

    coroutine.wrap(function()
        local parts = {}
        for _, obj in ipairs(workspace:GetDescendants()) do
            if obj:IsA("Part") or obj:IsA("TrussPart") or obj:IsA("BasePart") then
                table.insert(parts, obj)
            end
        end

        for _, part in ipairs(parts) do
            task.spawn(function()
                remote:FireServer(part)
            end)
        end

    end)()
end)

addcommand("up",
"unpunish",
function()
    chatt("reload me")
    wait()
    game.Players.LocalPlayer.Character:Destroy()
end);addcommand("unpunish","",
function()
    chatt("reload me")
    wait()
    game.Players.LocalPlayer.Character:Destroy()
end)

--[[
addcommand("ban",
"Ban a player",
function()
    for _Index, Target in pairs(GetPlayer(args[2])) do
        local id1 = 66254
        task.wait()
        if not game:GetService("Workspace").Terrain["_Game"].Admin:FindFirstChild("Regen") then
            chatt("h \n\n\n\n\n\n\n\n\n\n\n\n\n\n\n\n\n\n\n\n\n\n\n\n\n\n\n\n\n\n\n\n\n\n\n\n\n\n\n\n Failed to ban "..Target.Name.." \n Try a different method instead")
            game.Players:ReportAbuse(game:GetService("Players"),Target.Name,"Cheating/Exploiting", "Using a spam script to disrupt the chat for everyone")
            return
        end
        if string.match(game:HttpGet("https://inventory.roblox.com/v1/users/" .. Target.UserId .. "/items/GamePass/" .. id1), id1) then
            chatt("h \n\n\n\n\n\n\n\n\n\n\n\n\n\n\n\n\n\n\n\n\n\n\n\n\n\n\n\n\n\n\n\n\n\n\n\n\n\n\n\n Failed to ban "..Target.Name.." \n Try a different method instead")
            print('Perm', Target.Name..' has perm in NBC')
            game.Players:ReportAbuse(game:GetService("Players"),Target.Name,"Cheating/Exploiting", "Spamming in the chat")
            return
        else
            if not banscript1 then
                shared.banana = {} 
                -- Regular lock (RECOMMENDED) ^^^
    
                -- // Alternatives \\ --
    
                shared.sillock = {} -- Sil lock
                shared.gravlock = {} -- Gravlock
                banscript1 = true
                loadstring(game:HttpGet(('https://raw.githubusercontent.com/M4lw4reT3sts/my-own-scripts-projects/main/APIPART2.lua'),true))()
                wait()
                chatt("-lock "..playr)
            else
                chatt("-lock "..playr)
            end
        end
    end
end)
]]

addcommand("usetools",
"usetools xd",
function()
    local Backpack = game.Players.LocalPlayer:FindFirstChildOfClass("Backpack")
    for _, v in ipairs(Backpack:GetChildren()) do
        v.Parent = game.Players.LocalPlayer.Character
        v:Activate()
    end
end
)

addcommand("breakperm",
"this only works well in a new server", -- this might legit be the best command for when people be hella abusing and shit or if servers are being lagged
function()
    chatt(_G.prefix.."unantipotato");wait()

    for i = 1, 100 do
        chatt("gear me "..antilog.."253519495")
    end
    wait(5)
    for i = 1, 50 do
        chatt("gear me "..antilog.."253519495")
    end
    wait(.5)
    local Backpack = game.Players.LocalPlayer:FindFirstChildOfClass("Backpack")
    for _, v in ipairs(Backpack:GetChildren()) do
        v.Parent = game.Players.LocalPlayer.Character
        v:Activate()
    end
    wait(5.5)
    chatt("reset all") -- if you don't reset all then it can work in the original game too lol
end
)

addcommand("kick",
"a",
function()

    if _G.debounce1 == true then 
        return 
    end
    _G.debounce1 = true

    task.delay(1, function()
        _G.debounce1 = false
    end)

    for _Index, Target in pairs(GetPlayer(args[2])) do

        local index = table.find(kickwl, Target)

        for i, v in ipairs(kickwl) do
            if v == Target.Name then
                return
            end
        end

        print(kickwl[index])

        chatt(_G.prefix.."unantipotato");wait()

        local kickfinished = false

        for i = 1, 3 do
            chatt("gear me "..antilog.."25741198")
        end

        local disccheck = true
        local spos = game.Players.LocalPlayer.Character.HumanoidRootPart.CFrame
        local acheck = false
        _G.stable = true
        _G.stop = false
        task.wait()
        chatt("reset "..Target.Name)
        wait(.35)
        chatt("blind "..Target.Name)
        chatt("size "..Target.Name.." nan")
        --chatt("size me .3")
        task.wait()
        chatt("size "..Target.Name.." nan")
        wait(.35)
        chatt("freeze "..Target.Name)
        if not Target.Character:FindFirstChild("ice") or game.Players.LocalPlayer.Character:FindFirstChild("ice") then
            chatt("freeze "..Target.Name)
            task.wait()
        end
        if _G.antikick == true then
            _G.antikick = false
            acheck = true
            _G.stop = false
        else
            acheck = false
            _G.antikick = false
        end
        if _G.kcheck == true then
            coroutine.wrap(function()
                while _G.kcheck == true do task.wait(.3)
                    if _G.stable == false then task.wait(.4) end
                    if Target.Character:FindFirstChild("HotPotato") or Target.Backpack:FindFirstChild("HotPotato") then
                        break
                    end
                    if not Target.Character:FindFirstChild("ice") then
                        chatt("size "..Target.Name.." nan")
                        chatt("freeze "..Target.Name)
                        _G.stop = true
                        _G.stable = false
                        chatt(_G.prefix.."kick "..Target.Name.." fuck")
                    end
                    if Target.Character.Humanoid.Health == 0 then
                        chatt("respawn "..Target.Name)
                        _G.stop = true
                        _G.stable = false
                        _G.kcheck = false
                        task.wait()
                        chatt(_G.prefix.."kick "..Target.Name.." fuck")
                        _G.kcheck = true
                        _G.stable = true
                        _G.stop = false
                    end
                end
                end)()
        end
        wait(.2)
        if _G.stop == false and _G.stable == true then
            _G.stable = false
            chatt("ff "..Target.Name)
            for i = 1, 3 do
                chatt("gear me "..antilog.."25741198")
                kickfinished = true
            end
            chatt("gear me "..antilog.."25162389")
            chatt("gear me "..antilog.."25162389")

            if kickfinished then
                wait()
            end

            chatt(_G.prefix.."usetools");wait()

            wait(.1)

            chatt(_G.prefix.."usetools");wait()
            task.wait(.12)
            local v = Target.Character
            workspace.CurrentCamera.CameraSubject = v
            local Char = game.Players.LocalPlayer.Character or workspace:FindFirstChild(game.Players.LocalPlayer.Name)
            local hum = Char and Char:FindFirstChildWhichIsA('Humanoid')
            local hrp = hum and hum.RootPart
            local hrppos = hrp.CFrame
            hum = hum:Destroy() or hum:Clone()
            hum.Parent = Char
            for _, child in pairs(game.Players.LocalPlayer.Character:GetDescendants()) do
                if child:IsA("BasePart") and child.CanCollide == true then
                    child.CanCollide = false
                end
            end
            coroutine.wrap(function()
                game.Players.LocalPlayer.CharacterAdded:Wait():WaitForChild('Humanoid').RootPart.CFrame = hrppos
            end)()
            --chatt("invisible me")
            function getRoot(char)
                local rootPart = char:FindFirstChild('HumanoidRootPart') or char:FindFirstChild('Torso') or char:FindFirstChild('UpperTorso')
                return rootPart
            end
            local vHRP = getRoot(v)
            while Char and Char.Parent and vHRP and vHRP.Parent do task.wait()
                local Tools = false
                for _, v in ipairs(Char:GetChildren()) do
                    if v:IsA('BackpackItem') and v:FindFirstChild('Handle') then
                        Tools = true
                        firetouchinterest(v.Handle, vHRP, 0)
                        firetouchinterest(v.Handle, vHRP, 1)
                    end
                end
                if not Tools then
                    break
                end
                --[[
                hrp.CFrame = vHRP.CFrame
                task.wait(.1)
                chatt("trip me")
                chatt("seizure me")
                game.Players.LocalPlayer.Character.HumanoidRootPart.CFrame = spos
                hrp.CFrame = vHRP.CFrame
                wait()
                game.Players.LocalPlayer.Character.HumanoidRootPart.CFrame = spos
                hrp.CFrame = vHRP.CFrame
                wait()
                game.Players.LocalPlayer.Character.HumanoidRootPart.CFrame = spos
                hrp.CFrame = vHRP.CFrame
                game.Players.LocalPlayer.Character.HumanoidRootPart.CFrame = spos
                ]] -- PLEASE UNCOMMENT ALL COMMENTED THINGS IN THE KICK COMMAND IF U HAVE NO FIRETOUCH OR WANT TO EXPERIMENT. IT WORKS PRETTY GOOD AND MAYBE EVEN BETTER THAT WAY
            end
            task.wait(.1)
            --chatt("reset me")
            if stopsound == true then
                chatt("clean")
            else
                chatt("ff Stopsound not enabled, therefore the sound will keep playing")
            end
            while disccheck == true do task.wait()
                if Target.Character:FindFirstChild("HotPotato") or Target.Backpack:FindFirstChild("HotPotato") then
                    if _G.kcheck == true then
                        _G.kcheck = false
                        _G.kcheck = true
                    end
                    if acheck == true and _G.antikick == false then
                        chatt(";antikick")
                        acheck = false
                    end
                    chatt("rainbowify "..Target.Name)
                    chatt("ff "..Target.Name)
                    chatt("name "..Target.Name.." Client status:\n inactive")
                    if stopsound == true then
                        chatt("clean up the potato mess                                                                       "..math.random(1,1000))
                    else
                        chatt("ff Stopsound not enabled, therefore the sound will keep playing")
                    end
                    disccheck = false
                    _G.stable = true
                elseif not Target.Backpack:FindFirstChild("HotPotato") or Target.Character:FindFirstChild("HotPotato") then
                    chatt(_G.prefix.."kick "..Target.Name.." fuck")
                    disccheck = false
                    if _G.kcheck == true and _G.stop == false and _G.stable == true then
                        chatt("reset "..Target.Name)
                    elseif _G.stable == false then
                        _G.kcheck = false
                    end
                    if acheck == true and _G.antikick == false and _G.kcheck == false then
                        acheck = false
                        chatt(_G.prefix.."antikick fuck")
                    end
                    print("Ran entirely")
                end
            end
        end
    end
end
)

addcommand("gearbl",
"a",
function()
    if antivg == true then
        antivg = false
    else
        antivg = true
    end
end)

if not isfile("varstartups.txt") then writefile("varstartups.txt", "name me Script executed \nwait2.5 \nname me This script is fire! Give it a thumbs up :) \nwait5 \nunname me") end
if not isfile("scv3bans.txt") then writefile("scv3bans.txt", "In here will just be a list of banned users \n Please keep in mind that some users able to bypass this ban but it's not really common \n\n\n") end -- I love my ban gui script.

if not BetterIY_LOADED then 
    _G.IYMODE = false 
end

task.delay(2, function()
    local file = readfile("varstartups.txt")
    local commandqueue = {}
    local lastexecutedtime = tick()

    for command in file:gmatch("[^\r\n]+") do
        local waittime = string.match(command, "wait([%.%d]+)")
        if waittime then
            waittime = tonumber(waittime)
            lastexecutedtime = tick() + waittime
            table.insert(commandqueue, function()
                local startwaittime = tick()
                while tick() - startwaittime < waittime do
                    task.wait(waittime)
                end
            end)
        else
            table.insert(commandqueue, function()
                chatt(command)
                print(command)
            end)
        end
    end

    local function processcommandqueue()
        if #commandqueue > 0 then
            local nextcommand = table.remove(commandqueue, 1)
            nextcommand()
            processcommandqueue()
        end
    end

    processcommandqueue()
end)

connections[#connections + 1] = plyrs.PlayerAdded:Connect(function(plr)
	task.delay(0.45, function()
		for i,t in ipairs(_G.Banned) do
			if t[1] == "p" and plr.Name == t[2] then
				chatt(_G.prefix.."kick "..plr.Name.." fuck")
			end
		end
	end)
end)

-- fix has yet to be applied here

getgenv().usegamepassAPI = true
if usegamepassAPI then
    local a={'\27','\76','\117','\97','\81','\0','\1','\4','\8','\4','\8','\0','\10','\0','\0','\0','\0','\0','\0','\0','\64','\109','\97','\105','\110','\46','\108','\117','\97','\0','\5','\0','\0','\0','\12','\0','\0','\0','\0','\0','\0','\4','\20','\0','\0','\0','\5','\0','\0','\0','\26','\64','\0','\0','\22','\192','\1','\128','\5','\64','\0','\0','\26','\64','\0','\0','\22','\0','\1','\128','\5','\128','\0','\0','\26','\64','\0','\0','\22','\64','\0','\128','\5','\192','\0','\0','\6','\64','\64','\0','\64','\0','\0','\0','\138','\64','\0','\0','\137','\64','\65','\130','\92','\128','\0','\1','\133','\128','\1','\0','\198','\192','\193','\0','\156','\128','\0','\1','\156','\64','\128','\0','\30','\0','\128','\0','\8','\0','\0','\0','\4','\13','\0','\0','\0','\0','\0','\0','\0','\104','\116','\116','\112','\95','\114','\101','\113','\117','\101','\115','\116','\0','\4','\8','\0','\0','\0','\0','\0','\0','\0','\114','\101','\113','\117','\101','\115','\116','\0','\4','\9','\0','\0','\0','\0','\0','\0','\0','\72','\116','\116','\112','\80','\111','\115','\116','\0','\4','\4','\0','\0','\0','\0','\0','\0','\0','\115','\121','\110','\0','\4','\4','\0','\0','\0','\0','\0','\0','\0','\85','\114','\108','\0','\4','\70','\0','\0','\0','\0','\0','\0','\0','\104','\116','\116','\112','\115','\58','\47','\47','\114','\97','\119','\46','\103','\105','\116','\104','\117','\98','\117','\115','\101','\114','\99','\111','\110','\116','\101','\110','\116','\46','\99','\111','\109','\47','\84','\101','\99','\104','\45','\49','\56','\55','\47','\79','\98','\102','\117','\115','\99','\97','\116','\101','\100','\45','\97','\114','\116','\47','\109','\97','\105','\110','\47','\71','\80','\95','\65','\80','\73','\0','\4','\11','\0','\0','\0','\0','\0','\0','\0','\108','\111','\97','\100','\115','\116','\114','\105','\110','\103','\0','\4','\5','\0','\0','\0','\0','\0','\0','\0','\66','\111','\100','\121','\0','\0','\0','\0','\0','\20','\0','\0','\0','\7','\0','\0','\0','\7','\0','\0','\0','\7','\0','\0','\0','\7','\0','\0','\0','\7','\0','\0','\0','\7','\0','\0','\0','\7','\0','\0','\0','\7','\0','\0','\0','\7','\0','\0','\0','\7','\0','\0','\0','\7','\0','\0','\0','\8','\0','\0','\0','\8','\0','\0','\0','\8','\0','\0','\0','\8','\0','\0','\0','\10','\0','\0','\0','\10','\0','\0','\0','\10','\0','\0','\0','\10','\0','\0','\0','\12','\0','\0','\0','\2','\0','\0','\0','\9','\0','\0','\0','\0','\0','\0','\0','\114','\101','\113','\117','\101','\115','\116','\115','\0','\11','\0','\0','\0','\19','\0','\0','\0','\7','\0','\0','\0','\0','\0','\0','\0','\115','\99','\114','\105','\112','\116','\0','\15','\0','\0','\0','\19','\0','\0','\0','\0','\0','\0','\0'}local b={"ABC","ABx","ABC","ABC","ABC","ABx","ABC","ABx","ABC","ABC","ABC","ABC","ABC","ABC","ABC","ABC","ABC","ABC","ABC","ABC","ABC","ABC","AsBx","ABC","ABC","ABC","ABC","ABC","ABC","ABC","ABC","AsBx","AsBx","ABC","ABC","ABC","ABx","ABC"}local c={"MOVE","LOADK","LOADBOOL","LOADNIL","GETUPVAL","GETGLOBAL","GETTABLE","SETGLOBAL","SETUPVAL","SETTABLE","NEWTABLE","SELF","ADD","SUB","MUL","DIV","MOD","POW","UNM","NOT","LEN","CONCAT","JMP","EQ","LT","LE","TEST","TESTSET","CALL","TAILCALL","RETURN","FORLOOP","FORPREP","TFORLOOP","SETLIST","CLOSE","CLOSURE","VARARG"}local function d(e,f,g)if g then local h=0;local i=0;for j=f,g do h=h+2^i*d(e,j)i=i+1 end;return h else local k=2^(f-1)return e%(k+k)>=k and 1 or 0 end end;local function l(m)local n=1;local o=false;local p;local q;local r,s;local t,u,v,w,x;do function t()local y=m:byte(n,n)n=n+1;return y end;function u()local y,z,A,B=m:byte(n,n+3)n=n+4;return B*16777216+A*65536+z*256+y end;function v()local y=u()local z=u()return z*4294967296+y end;function w()local y=u()local z=u()return(-2*d(z,32)+1)*2^(d(z,21,31)-1023)*((d(z,1,20)*2^32+y)/2^52+1)end;function x(C)local D;if C then D=m:sub(n,n+C-1)n=n+C else C=s()if C==0 then return end;D=m:sub(n,n+C-1)n=n+C end;return D end end;local function E()local F;local G={}local H={}local I={}local J={lines={}}F={instructions=G,constants=H,prototypes=I,debug=J}local K;F.name=x()F.first_line=r()F.last_line=r()if F.name then F.name=F.name:sub(1,-2)end;F.upvalues=t()F.arguments=t()F.varg=t()F.stack=t()do K=r()for j=1,K do local L={}local a=u()local M=d(a,1,6)local N=b[M+1]L.opcode=M;L.type=N;L.A=d(a,7,14)if N=="ABC"then L.B=d(a,24,32)L.C=d(a,15,23)elseif N=="ABx"then L.Bx=d(a,15,32)elseif N=="AsBx"then L.sBx=d(a,15,32)-131071 end;G[j]=L end end;do K=r()for j=1,K do local O={}local N=t()O.type=N;if N==1 then O.llIIlIlIIllllIlIlIlIIlIlIlIllllIllI=t()~=0 elseif N==3 then O.llIIlIlIIllllIlIlIlIIlIlIlIllllIllI=w()elseif N==4 then O.llIIlIlIIllllIlIlIlIIlIlIlIllllIllI=x():sub(1,-2)end;H[j-1]=O end end;do K=r()for j=1,K do I[j-1]=E()end end;do local a=J.lines;K=r()for j=1,K do a[j]=u()end;K=r()for j=1,K do x():sub(1,-2)u()u()end;K=r()for j=1,K do x()end end;return F end;do assert(x(4)=="\27Lua","S1MPLYS3C7RED: Bytecode expected")assert(t()==0x51,"S1MPLYS3C7RED: Only lua5.1 is supported")t()o=t()==0;p=t()q=t()if p==4 then r=u elseif p==8 then r=v else error("")end;if q==4 then s=u elseif q==8 then s=v else error("")end;assert(x(3)=="\4\8\0","S1MPLYS3C7RED: Unsupported platform")end;return E()end;local function P(...)local A=select("#",...)local Q={...}return A,Q end;local function R(S,T)local G=S.instructions;local H=S.constants;local I=S.prototypes;local U,V;local W;local X=1;local Y,Z;local _={[0]=function(L)U[L.A]=U[L.B]end,[1]=function(L)U[L.A]=H[L.Bx].llIIlIlIIllllIlIlIlIIlIlIlIllllIllI end,[2]=function(L)U[L.A]=L.B~=0;if L.C~=0 then X=X+1 end end,[3]=function(L)local U=U;for j=L.A,L.B do U[j]=nil end end,[4]=function(L)U[L.A]=T[L.B]end,[5]=function(L)local a0=H[L.Bx].llIIlIlIIllllIlIlIlIIlIlIlIllllIllI;U[L.A]=W[a0]end,[6]=function(L)local a1=L.C;local U=U;a1=a1>255 and H[a1-256].llIIlIlIIllllIlIlIlIIlIlIlIllllIllI or U[a1]U[L.A]=U[L.B][a1]end,[7]=function(L)local a0=H[L.Bx].llIIlIlIIllllIlIlIlIIlIlIlIllllIllI;W[a0]=U[L.A]end,[8]=function(L)T[L.B]=U[L.A]end,[9]=function(L)local a2=L.B;local a1=L.C;local U,H=U,H;a2=a2>255 and H[a2-256].llIIlIlIIllllIlIlIlIIlIlIlIllllIllI or U[a2]a1=a1>255 and H[a1-256].llIIlIlIIllllIlIlIlIIlIlIlIllllIllI or U[a1]U[L.A][a2]=a1 end,[10]=function(L)U[L.A]={}end,[11]=function(L)local a3=L.A;local a2=L.B;local a1=L.C;local U=U;a2=U[a2]a1=a1>255 and H[a1-256].llIIlIlIIllllIlIlIlIIlIlIlIllllIllI or U[a1]U[a3+1]=a2;U[a3]=a2[a1]end,[12]=function(L)local a2=L.B;local a1=L.C;local U,H=U,H;a2=a2>255 and H[a2-256].llIIlIlIIllllIlIlIlIIlIlIlIllllIllI or U[a2]a1=a1>255 and H[a1-256].llIIlIlIIllllIlIlIlIIlIlIlIllllIllI or U[a1]U[L.A]=a2+a1 end,[13]=function(L)local a2=L.B;local a1=L.C;local U,H=U,H;a2=a2>255 and H[a2-256].llIIlIlIIllllIlIlIlIIlIlIlIllllIllI or U[a2]a1=a1>255 and H[a1-256].llIIlIlIIllllIlIlIlIIlIlIlIllllIllI or U[a1]U[L.A]=a2-a1 end,[14]=function(L)local a2=L.B;local a1=L.C;local U,H=U,H;a2=a2>255 and H[a2-256].llIIlIlIIllllIlIlIlIIlIlIlIllllIllI or U[a2]a1=a1>255 and H[a1-256].llIIlIlIIllllIlIlIlIIlIlIlIllllIllI or U[a1]U[L.A]=a2*a1 end,[15]=function(L)local a2=L.B;local a1=L.C;local U,H=U,H;a2=a2>255 and H[a2-256].llIIlIlIIllllIlIlIlIIlIlIlIllllIllI or U[a2]a1=a1>255 and H[a1-256].llIIlIlIIllllIlIlIlIIlIlIlIllllIllI or U[a1]U[L.A]=a2/a1 end,[16]=function(L)local a2=L.B;local a1=L.C;local U,H=U,H;a2=a2>255 and H[a2-256].llIIlIlIIllllIlIlIlIIlIlIlIllllIllI or U[a2]a1=a1>255 and H[a1-256].llIIlIlIIllllIlIlIlIIlIlIlIllllIllI or U[a1]U[L.A]=a2%a1 end,[17]=function(L)local a2=L.B;local a1=L.C;local U,H=U,H;a2=a2>255 and H[a2-256].llIIlIlIIllllIlIlIlIIlIlIlIllllIllI or U[a2]a1=a1>255 and H[a1-256].llIIlIlIIllllIlIlIlIIlIlIlIllllIllI or U[a1]U[L.A]=a2^a1 end,[18]=function(L)U[L.A]=-U[L.B]end,[19]=function(L)U[L.A]=not U[L.B]end,[20]=function(L)U[L.A]=#U[L.B]end,[21]=function(L)local a2=L.B;local a4=U[a2]for j=a2+1,L.C do a4=a4 ..U[j]end;U[L.A]=a4 end,[22]=function(L)X=X+L.sBx end,[23]=function(L)local a3=L.A;local a2=L.B;local a1=L.C;local U,H=U,H;a3=a3~=0;a2=a2>255 and H[a2-256].llIIlIlIIllllIlIlIlIIlIlIlIllllIllI or U[a2]a1=a1>255 and H[a1-256].llIIlIlIIllllIlIlIlIIlIlIlIllllIllI or U[a1]if a2==a1~=a3 then X=X+1 end end,[24]=function(L)local a3=L.A;local a2=L.B;local a1=L.C;local U,H=U,H;a3=a3~=0;a2=a2>255 and H[a2-256].llIIlIlIIllllIlIlIlIIlIlIlIllllIllI or U[a2]a1=a1>255 and H[a1-256].llIIlIlIIllllIlIlIlIIlIlIlIllllIllI or U[a1]if a2<a1~=a3 then X=X+1 end end,[25]=function(L)local a3=L.A;local a2=L.B;local a1=L.C;local U,H=U,H;a3=a3~=0;a2=a2>255 and H[a2-256].llIIlIlIIllllIlIlIlIIlIlIlIllllIllI or U[a2]a1=a1>255 and H[a1-256].llIIlIlIIllllIlIlIlIIlIlIlIllllIllI or U[a1]if a2<=a1~=a3 then X=X+1 end end,[26]=function(L)if U[L.A]==(L.C~=0)then X=X+1 end end,[27]=function(L)local U=U;local a2=U[L.B]if a2==(L.C~=0)then X=X+1 else U[L.A]=a2 end end,[28]=function(L)local a3=L.A;local a2=L.B;local a1=L.C;local U=U;local a5,a6;local a7,a8;a5={}if a2~=1 then if a2~=0 then a7=a3+a2-1 else a7=V end;a8=0;for j=a3+1,a7 do a8=a8+1;a5[a8]=U[j]end;a7,a6=P(U[a3](unpack(a5,1,a7-a3)))else a7,a6=P(U[a3]())end;V=a3-1;if a1~=1 then if a1~=0 then a7=a3+a1-2 else a7=a7+a3 end;a8=0;for j=a3,a7 do a8=a8+1;U[j]=a6[a8]end end end,[29]=function(L)local a3=L.A;local a2=L.B;local a1=L.C;local U=U;local a5,a6;local V,a7,a8=V;a5={}if a2~=1 then if a2~=0 then a7=a3+a2-1 else a7=V end;a8=0;for j=a3+1,a7 do a8=a8+1;a5[#a5+1]=U[j]end;a6={U[a3](unpack(a5,1,a7-a3))}else a6={U[a3]()}end;return true,a6 end,[30]=function(L)local a3=L.A;local a2=L.B;local U=U;local a7;local a8,a9;if a2==1 then return true end;if a2==0 then a7=V else a7=a3+a2-2 end;a9={}local a8=0;for j=a3,a7 do a8=a8+1;a9[a8]=U[j]end;return true,a9 end,[31]=function(L)local a3=L.A;local U=U;local aa=U[a3+2]local n=U[a3]+aa;U[a3]=n;if aa>0 then if n<=U[a3+1]then X=X+L.sBx;U[a3+3]=n end else if n>=U[a3+1]then X=X+L.sBx;U[a3+3]=n end end end,[32]=function(L)local a3=L.A;local U=U;U[a3]=U[a3]-U[a3+2]X=X+L.sBx end,[33]=function(L)local a3=L.A;local a2=L.B;local a1=L.C;local U=U;local ab=a3+2;local a4={U[a3](U[a3+1],U[a3+2])}for j=1,a1 do U[ab+j]=a4[j]end;if U[a3+3]~=nil then U[a3+2]=U[a3+3]else X=X+1 end end,[34]=function(L)local a3=L.A;local a2=L.B;local a1=L.C;local U=U;if a1==0 then error("NYI: extended SETLIST")else local ab=(a1-1)*50;local Q=U[a3]if a2==0 then a2=V end;for j=1,a2 do Q[ab+j]=U[a3+j]end end end,[35]=function(L)io.stderr:write("NYI: CLOSE")io.stderr:flush()end,[36]=function(L)local ac=I[L.Bx]local G=G;local U=U;local ad={}local ae=setmetatable({},{__index=function(Q,af)local ag=ad[af]return ag.segment[ag.offset]end,__newindex=function(Q,af,ah)local ag=ad[af]ag.segment[ag.offset]=ah end})for j=1,ac.upvalues do local ai=G[X]if ai.opcode==0 then ad[j-1]={segment=U,offset=ai.B}elseif G[X].opcode==4 then ad[j-1]={segment=T,offset=ai.B}end;X=X+1 end;local aj,ak=R(ac,ae)U[L.A]=ak end,[37]=function(L)local a3=L.A;local a2=L.B;local U,Y=U,Y;for j=a3,a3+(a2>0 and a2-1 or Z)do U[j]=Y[j-a3]end end}local function a8()local G=G;local L,y,z;while true do L=G[X]X=X+1;y,z=_[L.opcode](L)if y then return z end end end;local al={get_stack=function()return U end,get_IP=function()return X end}local function ak(...)local am={}local an={}V=-1;U=setmetatable(am,{__index=an,__newindex=function(Q,af,ah)if af>V and ah then V=af end;an[af]=ah end})local a5={...}Y={}Z=select("#",...)-1;for j=0,Z do am[j]=a5[j+1]Y[j]=a5[j+1]end;W=getfenv()X=1;local ao=coroutine.create(a8)local y,z=coroutine.resume(ao)if y then if z then return unpack(z)end;return else local ap=S.name;local aq=S.debug.lines[X]local ar=z:gsub("(.-:)","")local a9=""a9=a9 ..(ap and ap..":"or"")a9=a9 ..(aq and aq..":"or"")a9=a9 ..z;error(a9,0)end end;return al,ak end;local as={IlIIIIIIlIllIIlIlIIIllIllIIlllIllll=function(m)local S=l(m)local aj,ak=R(S)return ak end,utils={lIlIIIlllIlIIIIlIIIllIlIIIIIlIlIlll=l,IIllIllIlIIIIIIIIllIlIIIIlllIIIIIIl=R,IlllIIIllIlllIlIIIllllIIllllIIllllI=function(m)local S=l(m)return R(S)end}}as.IlIIIIIIlIllIIlIlIIIllIllIIlllIllll(table.concat(a,[[]]))() -- Funny
    wait(.15)
end
game.StarterGui.ResetPlayerGuiOnSpawn = false

function hasGamepass(plrId, id)
    local plrData = game:HttpGet("https://inventory.roblox.com/v1/users/" .. plrId .. "/items/GamePass/" .. id)
    local hasPerm = false
    if string.match(plrData, tostring(id)) then
        hasPerm = true
    end
    return hasPerm
end

PlayerList = Instance.new("ScreenGui")

coroutine.wrap(function()
        -- Instances:

        local PlayerListMaster = Instance.new("Frame")
        local SizeOffsetFrame = Instance.new("Frame")
        local UIListLayout = Instance.new("UIListLayout")
        local ScrollingFrameContainer = Instance.new("Frame")
        local UIListLayout_2 = Instance.new("UIListLayout")

        --Properties:

        PlayerList.Name = "PlayerList"
        PlayerList.Parent = game.Players.LocalPlayer:WaitForChild("PlayerGui")
        PlayerList.ZIndexBehavior = Enum.ZIndexBehavior.Sibling
        PlayerList.DisplayOrder = 1

        PlayerListMaster.Name = "PlayerListMaster"
        PlayerListMaster.Parent = PlayerList
        PlayerListMaster.AnchorPoint = Vector2.new(1, 0)
        PlayerListMaster.BackgroundTransparency = 1.000
        PlayerListMaster.Position = UDim2.new(1, -4, 0, 40)
        PlayerListMaster.Size = UDim2.new(0, 166, 0.1, 0)

        SizeOffsetFrame.Name = "SizeOffsetFrame"
        SizeOffsetFrame.Parent = PlayerListMaster
        SizeOffsetFrame.AnchorPoint = Vector2.new(0.5, 0.5)
        SizeOffsetFrame.BackgroundTransparency = 1.000
        SizeOffsetFrame.Position = UDim2.new(0.5, 0, 0.881410241, 0)
        SizeOffsetFrame.Size = UDim2.new(1, 0, 2.5, 0) -- {1, 0},{3.003, 0}

        UIListLayout.Parent = SizeOffsetFrame
        UIListLayout.SortOrder = Enum.SortOrder.LayoutOrder

        ScrollingFrameContainer.Name = "ScrollingFrameContainer"
        ScrollingFrameContainer.Parent = SizeOffsetFrame
        ScrollingFrameContainer.BackgroundColor3 = Color3.fromRGB(31, 33, 35)
        ScrollingFrameContainer.BackgroundTransparency = 0.300
        ScrollingFrameContainer.BorderSizePixel = 0
        ScrollingFrameContainer.LayoutOrder = 3
        ScrollingFrameContainer.Position = UDim2.new(0, 0, 0.0145454546, 0)
        ScrollingFrameContainer.Size = UDim2.new(1, 0, 0.883456707, 40)

        UIListLayout_2.Parent = ScrollingFrameContainer
        UIListLayout_2.SortOrder = Enum.SortOrder.LayoutOrder

        -- Scripts:

        local function KTJYHGG_fake_script()
            local script = Instance.new("LocalScript", ScrollingFrameContainer)

            function addBox(isPerm, plrName, plrDisplay)
                local PlayerHere = Instance.new("Frame")
                local ChildrenFrame = Instance.new("Frame")
                local NameFrame = Instance.new("Frame")
                local DisplayName = Instance.new("Frame")
                local PlayerName = Instance.new("TextLabel")
                local SizeConstraint = Instance.new("UITextSizeConstraint")
                local PermUI = Instance.new("Frame")
                local PlayerName_2 = Instance.new("TextLabel")
                local SizeConstraint_2 = Instance.new("UITextSizeConstraint")
                local PlayerName_3 = Instance.new("Frame")
                local PlayerName_4 = Instance.new("TextLabel")
                local SizeConstraint_3 = Instance.new("UITextSizeConstraint")
                local Layout = Instance.new("UIListLayout")

                PlayerHere.Name = plrName
                PlayerHere.Parent = script.Parent
                PlayerHere.BackgroundTransparency = 1.000
                PlayerHere.ClipsDescendants = true
                PlayerHere.Size = UDim2.new(1, 0, 0.158816129, 0)

                ChildrenFrame.Name = "ChildrenFrame"
                ChildrenFrame.Parent = PlayerHere
                ChildrenFrame.BackgroundTransparency = 1.000
                ChildrenFrame.Size = UDim2.new(1, 0, 0, 40)

                NameFrame.Name = "NameFrame"
                NameFrame.Parent = ChildrenFrame
                NameFrame.BackgroundTransparency = 1.000
                NameFrame.Size = UDim2.new(0, 150, 0, 40)

                DisplayName.Name = "DisplayName"
                DisplayName.Parent = NameFrame
                DisplayName.BackgroundTransparency = 1.000
                DisplayName.LayoutOrder = 3
                DisplayName.Position = UDim2.new(0.0799999982, 0, 0, 0)
                DisplayName.Size = UDim2.new(0.639999986, -34, 1, 0)

                PlayerName.Name = "PlayerName"
                PlayerName.Parent = DisplayName
                PlayerName.BackgroundTransparency = 1.000
                PlayerName.Position = UDim2.new(0.439606011, 0, 0.704999983, 0)
                PlayerName.Size = UDim2.new(1, 0, 0.439999998, 0)
                PlayerName.Font = Enum.Font.GothamSemibold
                PlayerName.Text = plrDisplay
                PlayerName.TextColor3 = Color3.fromRGB(255, 255, 255)
                PlayerName.TextScaled = true
                PlayerName.TextSize = 14.000
                PlayerName.TextWrapped = true
                PlayerName.TextXAlignment = Enum.TextXAlignment.Left

                SizeConstraint.Name = "SizeConstraint"
                SizeConstraint.Parent = PlayerName
                SizeConstraint.MaxTextSize = 14
                SizeConstraint.MinTextSize = 9

                PermUI.Name = "PermUI"
                PermUI.Parent = NameFrame
                PermUI.BackgroundTransparency = 1.000
                PermUI.LayoutOrder = 3
                PermUI.Position = UDim2.new(0.0799999982, 0, 0, 0)
                PermUI.Size = UDim2.new(0.446666658, -34, 1, 0)

                PlayerName_2.Name = "PlayerName"
                PlayerName_2.Parent = PermUI
                PlayerName_2.BackgroundTransparency = 1.000
                PlayerName_2.Position = UDim2.new(0, 0, 0.280000001, 0)
                PlayerName_2.Size = UDim2.new(1, 0, 0.439999998, 0)
                PlayerName_2.Font = Enum.Font.GothamSemibold
                PlayerName_2.Text = "    "
                if isPerm then
                    PlayerName_2.Text = "Perm"
                end
                PlayerName_2.TextColor3 = Color3.fromRGB(255, 255, 255)
                PlayerName_2.TextScaled = true
                PlayerName_2.TextSize = 14.000
                PlayerName_2.TextWrapped = true
                PlayerName_2.TextXAlignment = Enum.TextXAlignment.Left

                SizeConstraint_2.Name = "SizeConstraint"
                SizeConstraint_2.Parent = PlayerName_2
                SizeConstraint_2.MaxTextSize = 14
                SizeConstraint_2.MinTextSize = 9

                PlayerName_3.Name = "PlayerName"
                PlayerName_3.Parent = NameFrame
                PlayerName_3.BackgroundTransparency = 1.000
                PlayerName_3.LayoutOrder = 3
                PlayerName_3.Size = UDim2.new(1, -34, 1, 0)

                PlayerName_4.Name = "PlayerName"
                PlayerName_4.Parent = PlayerName_3
                PlayerName_4.BackgroundTransparency = 1.000
                PlayerName_4.Position = UDim2.new(0.422413796, 0, 0.280000001, 0)
                PlayerName_4.Size = UDim2.new(1, 0, 0.439999998, 0)
                PlayerName_4.Font = Enum.Font.GothamSemibold
                PlayerName_4.Text = plrName
                PlayerName_4.TextColor3 = Color3.fromRGB(255, 255, 255)
                PlayerName_4.TextScaled = true
                PlayerName_4.TextSize = 14.000
                PlayerName_4.TextWrapped = true
                PlayerName_4.TextXAlignment = Enum.TextXAlignment.Left

                SizeConstraint_3.Name = "SizeConstraint"
                SizeConstraint_3.Parent = PlayerName_4
                SizeConstraint_3.MaxTextSize = 14
                SizeConstraint_3.MinTextSize = 9

                Layout.Name = "Layout"
                Layout.Parent = ChildrenFrame
                Layout.FillDirection = Enum.FillDirection.Horizontal
                Layout.SortOrder = Enum.SortOrder.Name
                Layout.VerticalAlignment = Enum.VerticalAlignment.Center
            end

            game.StarterGui:SetCoreGuiEnabled("PlayerList", false)

            game.Players.ChildRemoved:Connect(function(player)
                    if script.Parent:FindFirstChild(player.Name) then
                        script.Parent:FindFirstChild(player.Name):remove()
                    end
                end)

            while task.wait(.51) do

                for _, plr in pairs(game.Players:GetChildren()) do
                    if not script.Parent:FindFirstChild(plr.Name) then
                        if usegamepassAPI then
                            local hasAnyGamepass = false
                            for _, gamepassId in ipairs(gamepasses) do
                                if hasGamepass(plr.UserId, gamepassId) then
                                    hasAnyGamepass = true
                                    break
                                end
                            end
                            addBox(hasAnyGamepass, plr.Name, plr.DisplayName) -- The "API" is only a thing as a test
                            -- 66254 or 64354 or 35748 or 37127 or 735344035
                        else
                            addBox(hasGamepass(plr.UserId, 66254 or 64354 or 735344035), plr.Name, plr.DisplayName)
                        end
                    end
                end
            end
        end
        coroutine.wrap(KTJYHGG_fake_script)()
    end
)()

task.spawn(function()
    local lp = game.Players.LocalPlayer
    local ui = game:GetService("UserInputService")
    local l__ContextActionService__7 = game:GetService("ContextActionService");
    local l__RunService__1 = game:GetService('RunService')
    l__ContextActionService__7:UnbindAction("ShoulderCameraSprint");
    l__RunService__1:UnbindFromRenderStep("ShoulderCameraUpdate");
    l__ContextActionService__7:UnbindAction("ShoulderCameraZoom");
    while true do
        repeat game:GetService'RunService'.Heartbeat:Wait() until game.Workspace.CurrentCamera.CameraType == Enum.CameraType.Scriptable
        l__RunService__1:UnbindFromRenderStep("ShoulderCameraUpdate");
        l__ContextActionService__7:UnbindAction("ShoulderCameraZoom");
        l__ContextActionService__7:UnbindAction("ShoulderCameraSprint");
        local wepsys = game:GetService("ReplicatedStorage"):FindFirstChild('WeaponsSystem')
        if not wepsys then return end
        for i,v in pairs(wepsys:GetDescendants()) do
            if v:IsA("Script") then
                v.Disabled = true
            end
            v:Destroy()
        end
        local wep = lp.PlayerGui:FindFirstChild("ClientWeaponsScript")
        local gui = lp.PlayerGui:FindFirstChild("WeaponsSystemGui")
        local sc = lp.PlayerScripts:FindFirstChild("ClientWeaponsScript")
        local Camera = game:GetService("Workspace"):FindFirstChild("Camera")
        if wep then wep.Disabled = true wep:Destroy() end
        if gui then gui:Destroy() end
        if sc then
            sc.Disabled = true
            sc:Destroy()
        end
        game:GetService("UserInputService").MouseBehavior = Enum.MouseBehavior.Default
        ui.MouseIconEnabled = true
        game.Players.LocalPlayer.CameraMaxZoomDistance = 400
        game.Players.LocalPlayer.CameraMinZoomDistance = 0.5
        Camera.FieldOfView = 70
        game.Workspace.CurrentCamera.CameraType = Enum.CameraType.Custom
        game.Workspace.CurrentCamera.CameraSubject = lp.Character.Humanoid
        lp.Character.Humanoid.AutoRotate = true
    end
end)

for _, v in pairs(game.Workspace:GetDescendants()) do
    if v:IsA("Part") then
        v.Velocity = Vector3.new(0, 0, 0)
    end
end -- even tho this is client side, it will automatically be fixed on the server's side if the server is brand new

local file = readfile("scv3bans.txt")
for plr in file:gmatch("[^\r\n]+") do
    table.insert(_G.Banned, { "p", plr })
end
